source2RSS_client/__init__.py
source2RSS_client/client.py
source2rss_client-0.1.1.dist-info/METADATA
source2rss_client-0.1.1.dist-info/WHEEL
source2rss_client-0.1.1.dist-info/top_level.txt
source2rss_client-0.1.1.dist-info/RECORD
