Metadata-Version: 2.4
Name: source2RSS_client
Version: 0.1.1
Summary: Client Program of source2RSS
Author-email: AhFei <vgamebox@outlook.com>
License: AGPL-3.0-only
Project-URL: Homepage, https://github.com/AhFeil/source2RSS
Project-URL: Issues, https://github.com/AhFeil/source2RSS/issues
Classifier: Programming Language :: Python :: 3
Classifier: Operating System :: OS Independent
Requires-Python: >=3.11
Requires-Dist: httpx>=0.27.0
